LICENSE
MANIFEST.in
README.md
setup.cfg
setup.py
cointk/__init__.py
cointk/backtest.py
cointk/data.py
cointk/init.py
cointk/order.py
cointk/prescient_sim.py
cointk.egg-info/PKG-INFO
cointk.egg-info/SOURCES.txt
cointk.egg-info/dependency_links.txt
cointk.egg-info/requires.txt
cointk.egg-info/top_level.txt
cointk/strategies/__init__.py
cointk/strategies/core.py
cointk/strategies/ema.py
cointk/strategies/naive.py
cointk/strategies/naive_reverse.py
cointk/strategies/simple_random.py
cointk/strategies/prescient/__init__.py
cointk/strategies/prescient/core.py
cointk/strategies/prescient/qty_independent.py
cointk/strategies/prescient/qty_semidependent.py