Metadata-Version: 1.0
Name: cointk
Version: 0.0.11
Summary: An open-sourced platform for rapid prototyping and testing of BitCoin trading strategies, with visualiaztion features via our open-sourced iOS app BitBox. Machine Learning algorithms coming Soon.
Home-page: http://github.com/CoinTK
Author: Alex Gajewski, Wanqi Zhu, Ashwin Aggarwal
Author-email: agajews@gmail.com, 1213.ghs@gmail.com, aaggarw99@gmail.com
License: MIT
Platform: UNKNOWN
